{"program_specialcolumn_算法专栏_数据结构之【链表】.md":"38545920","program_specialcolumn_算法专栏_算法二叉树基本概念.md":"0d7faf5c","program_specialcolumn_算法专栏_递归和分治.md":"77e9e77b","program_specialcolumn_设计模式专栏_体会面向对象和设计模式的几个例子.md":"cfbc614b","program_specialcolumn_设计模式专栏_前端_代理模式.md":"d7420cc2","program_specialcolumn_设计模式专栏_前端_单例模式.md":"abfbb1bf","program_specialcolumn_设计模式专栏_前端_原型模式.md":"2f52590a","program_specialcolumn_设计模式专栏_前端_工厂模式.md":"6094846c","program_specialcolumn_设计模式专栏_前端_装饰器模式.md":"eebe490a","program_specialcolumn_设计模式专栏_前端_观察者模式和发布订阅模式.md":"2ad472d2","program_specialcolumn_设计模式专栏_前端_迭代器模式.md":"36e7cd2b","program_specialcolumn_设计模式专栏_状态模式.md":"97714847","program_specialcolumn_设计模式专栏_设计原则.md":"430ed662","program_specialcolumn_设计模式专栏_设计模式汇总图.md":"1eabde39","program_specialcolumn_设计模式专栏_适配器模式.md":"5777ac27","tags.md":"75b3e52e","program_pieces_2021_01_05_伪元素遮罩层.md":"deb13ddb","others_interview_前端面试_react面试题.md":"b7d94479","others_interview_前端面试_vue面试题.md":"4fcad0ae","others_interview_前端面试_打包工具面试题.md":"93bcad60","program_issues_elementplus中resetfields方法无法移除下拉框校验结果.md":"74191e19","program_issues_mock服务器报跨域.md":"fe21ea54","program_issues_vscode如何指定eslint server运行在哪个版本的node.md":"1d89ffb2","program_issues_chrome调试时箭头函数内部this为undefined.md":"f795dfe0","program_issues_create-react-app新建的项目启动后浏览器报错.md":"b045254a","program_issues_fork的项目如何同步原仓库.md":"46ea3aff","program_issues_https协议网站访问音频http资源报错.md":"8f27de8b","program_issues_index.md":"07fec261","program_issues_低版本node项目升级高版本node启动报错.md":"ce3b9c5b","program_issues_多个窗口打开了同一网站-如何监听tab全部关闭.md":"17ae5bd1","program_issues_常见乱码原因.md":"46cbf881","program_issues_找不到全局类型array.md":"44fc0f37","program_issues_本站建设中图片弹出位置不居中.md":"e4dc5db2","program_issues_查看mac上java安装目录.md":"4f5d12b1","navlinks_index.md":"a133b629","program_pieces_2021_09_01_一个块元素的快速居中对齐.md":"a9ecfa2b","program_pieces_2021_09_01_从哪些点做性能优化.md":"7dec3a8f","program_pieces_2021_09_01_在浏览器输入url回车后都发生了什么.md":"0e89c9e6","program_pieces_2021_09_01_如何让谷歌浏览器支持小字体.md":"e15d935d","program_pieces_2021_09_01_常见的状态码以及post与get的区别.md":"15fbcfc5","program_pieces_2022_11_02_javascript函数式编程概念.md":"3d4f3d8f","program_pieces_2022_11_02_pnpm包管理器概念.md":"fd67bf12","program_pieces_2022_11_04_柯里化和偏应用概念.md":"98e762dc","program_pieces_2022_11_04_组合函数和管道基本概念.md":"47df858a","program_pieces_2022_11_07_dom自定义事件及冒泡与捕获.md":"6081f55a","program_pieces_2022_11_09_js代码的执行过程图.md":"5ed393ed","program_pieces_2022_11_09_js数组和weakmap.md":"6fe2702d","program_pieces_2022_11_09_js数组求交集并集差集.md":"0af3c1eb","program_pieces_2022_11_09_script标签上的常见属性解析.md":"8c78c5cd","program_pieces_2022_11_09_同源策略及跨域通信.md":"acd2575a","program_pieces_2022_11_09_迭代器和生成器.md":"36cdf97e","program_pieces_2022_12_01_了解js中有哪些事件.md":"832f35ed","program_pieces_2022_12_01_简单了解浏览器架构.md":"7a2d6519","program_pieces_2023_01_01_ts常用的一些类型.md":"91cb6cf4","program_pieces_2023_01_01_npm的安装机制.md":"847bdf67","program_pieces_2023_01_01_promise基础概念.md":"f06252f9","program_pieces_2023_03_07_tsconfig编译相关选项介绍.md":"a64f132b","program_pieces_2023_03_07_进制间的转换.md":"eb6fc3f0","program_pieces_2023_03_10_如何防止ts将相同形状的对象解释为同一种类型.md":"3e8b02cf","program_pieces_2023_03_23_滚动到浏览器视图某区域.md":"53dc72c7","program_pieces_2023_03_23_配置node项目支持es6模块.md":"9b7d8b7e","program_pieces_2023_03_24_docker常用命令.md":"0af2ea85","program_pieces_2023_03_24_生成项目目录树.md":"d006615f","program_pieces_2023_03_24_项目脚手架工具.md":"9f816da2","program_pieces_2023_04_24_sort比较函数记录.md":"bd9ccf67","program_pieces_2023_05_10_unocss学习梳理.md":"96c3cfd0","program_pieces_2023_05_15_无符号及有符号位移运算.md":"3c970e7a","program_pieces_2023_05_31_npm发布的常用命令.md":"1b4a5298","program_pieces_index.md":"8d68293a","program_specialcolumn_javascript专栏_es6789基本语法.md":"d4533147","program_specialcolumn_javascript专栏_javascript中常见的继承方式.md":"357bf19d","program_specialcolumn_javascript专栏_javascript作用域.md":"62629b54","program_specialcolumn_javascript专栏_javascript数据类型的种类检测及转换.md":"6f7f8014","program_specialcolumn_javascript专栏_javascript闭包.md":"699f74e7","program_specialcolumn_javascript专栏_new的原理和call和bind和apply.md":"f800832d","program_specialcolumn_javascript专栏_如何判断数据类型.md":"08a551af","program_specialcolumn_javascript专栏_手写js相关系列.md":"47be6567","program_specialcolumn_javascript专栏_深拷贝和浅拷贝.md":"c8e544ef","program_specialcolumn_java专栏_java程序的内存划分.md":"25dc497e","program_specialcolumn_index.md":"c6f9675b","program_specialcolumn_算法专栏_堆的基本概念.md":"0e301fb0","program_specialcolumn_算法专栏_数据结构.md":"8b35750d","program_specialcolumn_算法专栏_数据结构之【数组】.md":"be6c6005","program_pieces_2022_11_09_js中symbol和对象及内存管理.md":"bf918842","program_pieces_2023_04_11_canvas和svg的区别.md":"e6345455","others_interview_前端面试_框架应用题.md":"69d53735","program_pieces_2021_09_01_什么是浏览器重排与重绘.md":"42724982","about_index.md":"0ad05c79","archives.md":"e4bd6ada","blogs_index.md":"720269ba","blogs_人际交流的几点经验.md":"13d95679","books_socialsciences_index.md":"764976d2","books_socialsciences_佛陀传_文章摘抄.md":"4e07f1d6","books_socialsciences_佛陀传_随记1.md":"e9726404","program_issues_elementui中select组件搜索时第一个输入的字符自动清空.md":"c032f4d6","books_socialsciences_单核工作法_单核工作5原理.md":"693acd92","books_socialsciences_大周期：不确定时代的确定性生存法则_书摘.md":"97a2ba18","program_issues_element ui在浏览器缩放下多选下拉框换行抖动.md":"960fdf4c","books_socialsciences_置身事内_index.md":"270e6e44","books_techandcodes_css世界_css世界之_盒的诞生.md":"142a517d","books_techandcodes_css世界_css世界之内联元素.md":"3472fd6b","program_issues_vue2老项目本地迁移vite填坑.md":"dd1dc5ba","books_techandcodes_css世界_css世界之再看宽高.md":"21fe1ce7","books_techandcodes_css世界_css世界之宽度的小花活儿.md":"a018c40a","program_issues_监听pushstate和replacestate事件.md":"79d3ebde","books_techandcodes_css世界_css世界之来看看盒尺寸.md":"10d01941","books_techandcodes_css世界_css世界随记1.md":"21103cd3","books_techandcodes_javascript正则表达式迷你书_读书笔记脑图.md":"1e90f8e1","books_techandcodes_javascript高级程序设计_红宝书笔记之变量和迭代器.md":"4b94072c","books_techandcodes_index.md":"cf0dfcad","books_techandcodes_深入理解typescript_编译上下文_声明空间_模块.md":"71f8e40d","books_techandcodes_程序员的思维训练_程序员的思维训练文摘1.md":"84189853","books_techandcodes_程序员的思维训练_程序员的思维训练文摘2.md":"7354f0d7","books_techandcodes_程序员的思维训练_程序员的思维训练文摘3.md":"f8c03582","about_me.md":"7bdd8a8e","books_techandcodes_程序员的思维训练_程序员的思维训练文摘4.md":"649eecbf","program_issues_记一次vue版本升级带来的bug.md":"ac1c8fc5","books_techandcodes_深入理解typescript_ts环境声明.md":"744606c5","program_issues_记同事的一个bug及平常写代码注意点.md":"8e6a183d","books_techandcodes_程序员的思维训练_粗读第一遍读后感.md":"f656cff6","books_techandcodes_编程与类型系统_ts类型之数值类型.md":"38ddca31","books_techandcodes_程序员的思维训练_程序员的思维训练文摘5.md":"20ffbe98","books_techandcodes_编程与类型系统_ts类型之never与void.md":"589de0a8","index.md":"6870a2fd","program_pieces_2021_09_01_vm与百分比有什么区别.md":"df9cdd8f","books_techandcodes_javascript语言精髓与编程实践_js面向对象的特性.md":"cb3c73ad","books_techandcodes_javascript语言精髓与编程实践_等值比较.md":"2cb12113","books_techandcodes_javascript高级程序设计_红宝书之js函数和代理和闭包和期约.md":"5641805d","books_techandcodes_vue.js设计与实现_第一章笔记概述.md":"8c31ce8d","books_techandcodes_javascript高级程序设计_红宝书之对象和原型.md":"be07420f","others_hardware_index.md":"0d056675","others_hardware_树莓派.md":"3e201c11","others_interview_index.md":"8590a678","others_interview_前端面试_javascript面试题.md":"ca619627","program_pieces_2021_01_05_垂直外边距塌陷.md":"6e85bebe","program_pieces_2021_02_html特殊标签和特殊符号.md":"5715afa8","program_pieces_2021_03_02_github拉取其他项目并关联自己的远程库.md":"2bf00ca6","program_pieces_2021_03_02_git分支合并解决冲突.md":"f95e7775","program_pieces_2021_03_02_git比较文件差异及修改commit信息.md":"5bd0baf3","program_pieces_2021_07_01_ts装饰器.md":"730e3ffc","program_pieces_2021_08_04_ts中不要做的事.md":"fc1b88a7","program_pieces_2021_08_04_ts类型创建之泛型.md":"d1e4fa43","program_pieces_2021_08_04_ts类型工具.md":"df3ea782","program_pieces_2021_08_04_ts类型约束.md":"a5af1ddf","program_pieces_2021_08_04_typescript中感叹号和问号的含义.md":"04defa74","program_pieces_2021_09_01_html之_三栏布局_.md":"50295ecf"}
