{"program_pieces_2022_11_09_迭代器和生成器.md":"efd43e88","about_index.md":"94784c91","about_me.md":"a3803d66","archives.md":"cd39c9a7","blogs_index.md":"c04e5bf2","blogs_人际交流的几点经验.md":"aaf306b3","books_socialsciences_index.md":"4f454193","books_socialsciences_佛陀传_文章摘抄.md":"6ce42f40","books_socialsciences_佛陀传_随记1.md":"fd5099f5","books_socialsciences_单核工作法_单核工作5原理.md":"ce45b730","books_socialsciences_大周期：不确定时代的确定性生存法则_书摘.md":"71021341","books_socialsciences_置身事内_index.md":"9ac821a8","books_techandcodes_css世界_css世界之_盒的诞生.md":"892c4e0a","books_techandcodes_css世界_css世界之内联元素.md":"c2f42e5f","books_techandcodes_css世界_css世界之再看宽高.md":"25056b35","books_techandcodes_css世界_css世界之宽度的小花活儿.md":"c9039479","books_techandcodes_css世界_css世界之来看看盒尺寸.md":"283f544e","books_techandcodes_css世界_css世界随记1.md":"b435d25c","books_techandcodes_javascript正则表达式迷你书_读书笔记脑图.md":"a63924f6","books_techandcodes_javascript语言精髓与编程实践_js面向对象的特性.md":"ef64f9b1","books_techandcodes_javascript语言精髓与编程实践_等值比较.md":"7978d78b","books_techandcodes_javascript高级程序设计_红宝书之js函数和代理和闭包和期约.md":"31448216","books_techandcodes_javascript高级程序设计_红宝书之对象和原型.md":"5ac6262b","books_techandcodes_javascript高级程序设计_红宝书笔记之变量和迭代器.md":"843b269f","books_techandcodes_index.md":"05655b7b","books_techandcodes_深入理解typescript_ts环境声明.md":"ea1e01bc","books_techandcodes_深入理解typescript_编译上下文_声明空间_模块.md":"41ab20cb","books_techandcodes_程序员的思维训练_程序员的思维训练文摘1.md":"bb3bceff","books_techandcodes_程序员的思维训练_程序员的思维训练文摘2.md":"0d733caa","books_techandcodes_程序员的思维训练_程序员的思维训练文摘3.md":"ba52d1a3","books_techandcodes_程序员的思维训练_程序员的思维训练文摘4.md":"7d19f5ab","books_techandcodes_程序员的思维训练_程序员的思维训练文摘5.md":"f396ccab","books_techandcodes_程序员的思维训练_粗读第一遍读后感.md":"0b7dfd01","books_techandcodes_编程与类型系统_ts类型之never与void.md":"423fd82f","books_techandcodes_编程与类型系统_ts类型之数值类型.md":"ad9ae114","index.md":"08320ba2","navlinks_index.md":"c3248957","program_interview_index.md":"b66b672d","program_issues_elementui中select组件搜索时第一个输入的字符自动清空.md":"8a20b0dc","program_issues_mock服务器报跨域.md":"294e00cf","program_issues_vscode如何指定eslint server运行在哪个版本的node.md":"ef4af018","program_issues_chrome调试时箭头函数内部this为undefined.md":"992d7791","program_issues_create-react-app新建的项目启动后浏览器报错.md":"271dab94","program_issues_element ui在浏览器缩放下多选下拉框换行抖动.md":"7ce34f08","program_issues_fork的项目如何同步原仓库.md":"fb9c5121","program_issues_https协议网站访问音频http资源报错.md":"57994688","program_issues_index.md":"317d0bb7","program_issues_vue2老项目本地迁移vite填坑.md":"a782b232","program_issues_低版本node项目升级高版本node启动报错.md":"ddf0addd","program_issues_常见乱码原因.md":"79f37a37","program_issues_找不到全局类型array.md":"0d2f8b5c","program_issues_本站建设中图片弹出位置不居中.md":"59de442c","program_issues_查看mac上java安装目录.md":"408bc1d9","program_issues_监听pushstate和replacestate事件.md":"3507abec","program_issues_记同事的一个bug及平常写代码注意点.md":"a5513631","program_pieces_2021_01_05_垂直外边距塌陷.md":"fc6db7a0","program_pieces_2021_02_html特殊标签和特殊符号.md":"0b242037","program_pieces_2021_03_02_github拉取其他项目并关联自己的远程库.md":"be19b399","program_pieces_2021_03_02_git分支合并解决冲突.md":"85257816","program_pieces_2021_03_02_git比较文件差异及修改commit信息.md":"e64282ae","program_pieces_2021_07_01_ts装饰器.md":"ef74f9b7","program_pieces_2021_08_04_ts中不要做的事.md":"1f55c85f","program_pieces_2021_08_04_ts类型创建之泛型.md":"2cb9a541","program_pieces_2021_09_01_在浏览器输入url回车后都发生了什么.md":"c33343db","program_pieces_2022_11_02_pnpm包管理器概念.md":"74ab9d29","program_pieces_2022_11_04_柯里化和偏应用概念.md":"03261297","program_pieces_2022_11_04_组合函数和管道基本概念.md":"982061a1","program_pieces_2022_11_09_js中symbol和对象及内存管理.md":"5ab5d9d3","program_pieces_2022_11_09_js数组和weakmap.md":"fce9a277","program_pieces_2022_11_09_js数组求交集并集差集.md":"b4a3e5a3","program_pieces_2022_11_09_script标签上的常见属性解析.md":"2bb5a15a","program_pieces_2022_11_09_同源策略及跨域通信.md":"218d642b","program_pieces_2022_12_01_了解js中有哪些事件.md":"6e8baa17","program_pieces_2022_12_01_简单了解浏览器架构.md":"b02279b2","program_pieces_2023_01_01_ts常用的一些类型.md":"c6889e51","program_pieces_2023_01_01_npm的安装机制.md":"a7091944","program_pieces_2023_01_01_promise基础概念.md":"728dfb10","program_pieces_2021_09_01_html之_三栏布局_.md":"3a35b8dd","program_pieces_2022_11_02_javascript函数式编程概念.md":"d29fbaa7","books_techandcodes_vue.js设计与实现_第一章笔记概述.md":"3c9848bb","program_pieces_2023_03_10_如何防止ts将相同形状的对象解释为同一种类型.md":"f80f02c1","program_pieces_2023_03_23_滚动到浏览器视图某区域.md":"1e4a6257","program_pieces_2023_03_23_配置node项目支持es6模块.md":"74c0831a","program_pieces_2023_03_24_docker常用命令.md":"eef2b139","program_specialcolumn_javascript专栏_javascript作用域.md":"e5beb4ee","program_specialcolumn_javascript专栏_javascript数据类型的种类检测及转换.md":"1e8c5ba1","program_specialcolumn_javascript专栏_javascript闭包.md":"4aceec43","program_specialcolumn_javascript专栏_new的原理和call和bind和apply.md":"f732c9f4","program_specialcolumn_javascript专栏_如何判断数据类型.md":"ab86fb62","program_specialcolumn_javascript专栏_手写js相关系列.md":"014853b3","program_specialcolumn_javascript专栏_深拷贝和浅拷贝.md":"438c39ad","program_specialcolumn_算法专栏_堆的基本概念.md":"87efc8c4","program_specialcolumn_算法专栏_数据结构.md":"7bff2656","program_specialcolumn_设计模式专栏_体会面向对象和设计模式的几个例子.md":"20add086","program_specialcolumn_设计模式专栏_前端_代理模式.md":"85a06300","program_specialcolumn_设计模式专栏_前端_单例模式.md":"65382795","program_specialcolumn_设计模式专栏_前端_原型模式.md":"6a456050","program_specialcolumn_设计模式专栏_前端_工厂模式.md":"bd52f5a7","program_specialcolumn_设计模式专栏_前端_装饰器模式.md":"b949a496","program_specialcolumn_设计模式专栏_前端_观察者模式和发布订阅模式.md":"d4d02aa8","program_specialcolumn_设计模式专栏_前端_迭代器模式.md":"a3828fbf","program_specialcolumn_设计模式专栏_状态模式.md":"4c7f4b45","program_specialcolumn_设计模式专栏_设计原则.md":"3c1491f3","program_specialcolumn_设计模式专栏_设计模式汇总图.md":"ccce2d43","program_specialcolumn_设计模式专栏_适配器模式.md":"57ac0f2b","tags.md":"ef44cbc8","program_pieces_2022_11_07_dom自定义事件及冒泡与捕获.md":"0f191fcb","program_pieces_2022_11_09_js代码的执行过程图.md":"0afe9fe5","program_pieces_2021_09_01_vm与百分比有什么区别.md":"a4a24ee5","program_pieces_2023_04_24_sort比较函数记录.md":"542fc311","program_pieces_2021_09_01_一个块元素的快速居中对齐.md":"d66d4e0b","program_pieces_2021_09_01_如何让谷歌浏览器支持小字体.md":"99055c11","program_pieces_2023_05_10_unocss学习梳理.md":"e4949f40","program_pieces_2023_05_15_无符号及有符号位移运算.md":"2219e90b","program_pieces_2021_09_01_什么是浏览器重排与重绘.md":"5c412d0e","program_specialcolumn_算法专栏_算法二叉树基本概念.md":"10a8833a","program_pieces_2023_05_31_npm发布的常用命令.md":"f6553bef","program_pieces_index.md":"763e5ad5","program_pieces_2023_03_24_生成项目目录树.md":"30653fc9","program_pieces_2023_03_24_项目脚手架工具.md":"b5d414b1","program_pieces_2023_04_11_canvas和svg的区别.md":"0ec5fd38","program_pieces_2021_08_04_ts类型工具.md":"1e103555","program_pieces_2021_08_04_typescript中感叹号和问号的含义.md":"ae804d95","program_pieces_2023_03_07_tsconfig编译相关选项介绍.md":"ab1316de","program_pieces_2023_03_07_进制间的转换.md":"6775d624","program_specialcolumn_javascript专栏_es6789基本语法.md":"3343ff6a","program_pieces_2021_09_01_常见的状态码以及post与get的区别.md":"a6ec8054","program_specialcolumn_index.md":"75b0954a","program_specialcolumn_javascript专栏_javascript中常见的继承方式.md":"8da20467","program_pieces_2021_01_05_伪元素遮罩层.md":"b7444d3d","program_pieces_2021_08_04_ts类型约束.md":"d370b38e","program_pieces_2021_09_01_从哪些点做性能优化.md":"ce16ce87"}
